MANIFEST.in
README.md
setup.py
synergine/__init__.py
synergine/cst.py
synergine.egg-info/PKG-INFO
synergine.egg-info/SOURCES.txt
synergine.egg-info/dependency_links.txt
synergine.egg-info/top_level.txt
synergine/core/ActionManager.py
synergine/core/Core.py
synergine/core/CycleCalculator.py
synergine/core/Map.py
synergine/core/Signal.py
synergine/core/Signals.py
synergine/core/SpaceDataConnector.py
synergine/core/SynergyObjectManager.py
synergine/core/Test.py
synergine/core/__init__.py
synergine/core/exceptions.py
synergine/core/config/ConfigurationManager.py
synergine/core/config/__init__.py
synergine/core/connection/Connector.py
synergine/core/connection/Display.py
synergine/core/connection/Terminal.py
synergine/core/connection/__init__.py
synergine/core/cycle/Context.py
synergine/core/cycle/PipePackage.py
synergine/core/cycle/__init__.py
synergine/core/display/ObjectVisualizer.py
synergine/core/display/__init__.py
synergine/core/exception/NotFoundError.py
synergine/core/exception/__init__.py
synergine/core/process/__init__.py
synergine/core/simulation/EventManager.py
synergine/core/simulation/MetaCollections.py
synergine/core/simulation/MetaDatas.py
synergine/core/simulation/MetaStates.py
synergine/core/simulation/MetaSynergyCollections.py
synergine/core/simulation/MetaValue.py
synergine/core/simulation/__init__.py
synergine/core/simulation/mechanism/Mechanism.py
synergine/core/simulation/mechanism/__init__.py
synergine/display/TestDisplay.py
synergine/display/TwoDimensionalGrid.py
synergine/display/Visualisation.py
synergine/display/__init__.py
synergine/display/object/__init__.py
synergine/lib/__init__.py
synergine/lib/eint.py
synergine/lib/factory/__init__.py
synergine/lib/factory/factory.py
synergine/lib/process/__init__.py
synergine/lib/process/processmanager.py
synergine/lib/process/tool.py
synergine/synergy/Simulation.py
synergine/synergy/__init__.py
synergine/synergy/collection/Configuration.py
synergine/synergy/collection/SynergyCollection.py
synergine/synergy/collection/__init__.py
synergine/synergy/event/Action.py
synergine/synergy/event/ContactEvent.py
